trail/__init__.py
trail/main.py
trail/trail.py
trail/exception/__init__.py
trail/exception/auth.py
trail/exception/config.py
trail/exception/trail.py
trail/exception/upload.py
trail/libconfig/__init__.py
trail/libconfig/config.py
trail/userconfig/__init__.py
trail/userconfig/config.py
trail/userconfig/config_utils.py
trail/userconfig/init.py
trail/userconfig/search_config_file.py
trail/util/__init__.py
trail/util/add_test_coverage_results.py
trail/util/add_test_results.py
trail/util/auth.py
trail/util/gql_client.py
trail/util/new_experiment.py
trail/util/upload_artifacts_from_notebook.py
trail/util/uploads.py
trailml-1.2.2.dist-info/METADATA
trailml-1.2.2.dist-info/WHEEL
trailml-1.2.2.dist-info/entry_points.txt
trailml-1.2.2.dist-info/top_level.txt
trailml-1.2.2.dist-info/RECORD
