Metadata-Version: 2.4
Name: trailml
Version: 1.2.2
Summary: Trail ML library
Author-email: Trail ML <python@trail-ml.com>
Project-URL: Homepage, https://trail-ml.com
Project-URL: Bug Tracker, https://github.com/trail-ml/bugtracker/issues
Classifier: Programming Language :: Python :: 3
Classifier: License :: OSI Approved :: MIT License
Classifier: Operating System :: OS Independent
Requires-Python: >=3.7
Requires-Dist: gql
Requires-Dist: aiohttp
Requires-Dist: mlflow
Requires-Dist: PyYAML
Requires-Dist: requests-toolbelt==0.10.1
Requires-Dist: sentry-sdk
Requires-Dist: tqdm
Requires-Dist: nbformat
Requires-Dist: pydantic-settings>=2.0.0
